kwonly_args/__init__.py
kwonly_args/utils.py
kwonly_args-1.0.10.dist-info/DESCRIPTION.rst
kwonly_args-1.0.10.dist-info/METADATA
kwonly_args-1.0.10.dist-info/RECORD
kwonly_args-1.0.10.dist-info/WHEEL
kwonly_args-1.0.10.dist-info/metadata.json
kwonly_args-1.0.10.dist-info/top_level.txt
