Metadata-Version: 1.1
Name: kwonly-args
Version: 1.0.10
Summary: Python2 keyword-only argument emulation as a decorator. Python 3 compatible.
Home-page: https://github.com/pasztorpisti/kwonly-args
Author: István Pásztor
Author-email: pasztorpisti@gmail.com
License: MIT
Keywords: kwonly keyword only arguments args decorator
Platform: UNKNOWN
Classifier: License :: OSI Approved :: MIT License
Classifier: Development Status :: 5 - Production/Stable
Classifier: Intended Audience :: Developers
Classifier: Topic :: Software Development :: Libraries :: Python Modules
Classifier: Programming Language :: Python :: 2
Classifier: Programming Language :: Python :: 3
Classifier: Programming Language :: Python :: Implementation :: CPython
Classifier: Programming Language :: Python :: Implementation :: PyPy
